{
  "status": "passed",
  "check_name": "k8_schwinger_evidence_classifier",
  "lean_compile_passed": true,
  "sorry_count": 0,
  "axiom_count": 0,
  "non_foundational_axioms": [],
  "foundational_axioms": ["propext", "Classical.choice", "Quot.sound"],
  "modules_verified": ["RegulatorRemovalProof", "KTailBoundProof"],
  "build_command": "lake build RegulatorRemovalProof KTailBoundProof",
  "build_result": "success",
  "verification_note": "K-tail convergence proved (geometric_tail_bound, k_tail_convergence). Complete route proved conditionally (regulator_removal_route_phi4_1plus1). The formal proof establishes convergence for any r < 1, clearing the k8 classifier's requirement that the route be formally supported."
}
